notificationcenter/__init__.py
notificationcenter/_notificationcenter.py
notificationcenter/_version.py
notificationcenter-1.0.0b2.dist-info/DESCRIPTION.rst
notificationcenter-1.0.0b2.dist-info/METADATA
notificationcenter-1.0.0b2.dist-info/RECORD
notificationcenter-1.0.0b2.dist-info/WHEEL
notificationcenter-1.0.0b2.dist-info/metadata.json
notificationcenter-1.0.0b2.dist-info/top_level.txt
