Metadata-Version: 1.1
Name: notificationcenter
Version: 1.0.0b2
Summary: Port of NSNotificationCenter functionality to Python
Home-page: UNKNOWN
Author: ti250
Author-email: ti250@cam.ac.uk
License: BSD
Keywords: notifications observer
Platform: UNKNOWN
Classifier: Development Status :: 4 - Beta
Classifier: Intended Audience :: Developers
Classifier: Topic :: Software Development :: Libraries :: Python Modules
Classifier: License :: OSI Approved :: BSD License
Classifier: Programming Language :: Python :: 3.5
